sage_package/__init__.py
sage_package/setuptools.py
sage_package/sphinx.py
sage_package/themes/sage/layout.html
sage_package/themes/sage/search.html
sage_package/themes/sage/thebe.html
sage_package/themes/sage/theme.conf
sage_package/themes/sage/static/README
sage_package/themes/sage/static/favicon.ico
sage_package/themes/sage/static/mathjax_sage.js_t
sage_package/themes/sage/static/sage.css_t
sage_package/themes/sage/static/sageicon.png
sage_package/themes/sage/static/sagelogo.png
sage_package/themes/sage/static/thebe-sage.js
sage_package/themes/sage/static/thebe_status_field.css
sage_package/themes/sage/static/thebe_status_field.js
sage_package/themes/sageref/layout.html
sage_package/themes/sageref/theme.conf
sage_package/themes/sageref/static/favicon.ico
sage_package/themes/sageref/static/mathjax_sage.js_t
sage_package/themes/sageref/static/sage.css_t
sage_package/themes/sageref/static/thebe-sage.js
sage_package-0.0.6.dist-info/DESCRIPTION.rst
sage_package-0.0.6.dist-info/METADATA
sage_package-0.0.6.dist-info/RECORD
sage_package-0.0.6.dist-info/WHEEL
sage_package-0.0.6.dist-info/entry_points.txt
sage_package-0.0.6.dist-info/metadata.json
sage_package-0.0.6.dist-info/top_level.txt
