Metadata-Version: 2.0
Name: sage-package
Version: 0.0.6
Summary: Utilities for authoring SageMath packages
Home-page: https://github.com/sagemath/sage-package
Author: Nicolas M. Thiéry et al.
Author-email: nthiery@users.sf.net
License: GPLv2+
Keywords: SageMath,Sphinx,packaging
Platform: UNKNOWN
Classifier: Development Status :: 4 - Beta
Classifier: Intended Audience :: Science/Research
Classifier: Topic :: Software Development :: Build Tools
Classifier: Topic :: Scientific/Engineering :: Mathematics
Classifier: License :: OSI Approved :: GNU General Public License v2 or later (GPLv2+)
Classifier: Programming Language :: Python :: 2.7
